sila2codegenerator/VERSION
sila2codegenerator/__init__.py
sila2codegenerator/__meta__.py
sila2codegenerator/service_descriptor_parser.py
sila2codegenerator/sila2codegenerator.py
sila2codegenerator/PrototypeGenerator/ClientPrototypeGenerator.py
sila2codegenerator/PrototypeGenerator/FDLPrototypeGenerator.py
sila2codegenerator/PrototypeGenerator/ImplementationPrototypeGenerator.py
sila2codegenerator/PrototypeGenerator/PrototypeGenerator.py
sila2codegenerator/PrototypeGenerator/ServerPrototypeGenerator.py
sila2codegenerator/PrototypeGenerator/ServicerPrototypeGenerator.py
sila2codegenerator/PrototypeGenerator/__init__.py
sila2codegenerator/PrototypeGenerator/generate_defaults.py
sila2codegenerator/PrototypeGenerator/tests/__init__.py
sila2codegenerator/PrototypeGenerator/tests/test_generate_defaults.py
sila2codegenerator/templates/run-inline/command_observable_intermediate_call.pyt
sila2codegenerator/templates/run-inline/command_observable_intermediate_implementation.pyt
sila2codegenerator/templates/run-inline/command_observable_intermediate_servicer.pyt
sila2codegenerator/templates/run-inline/command_observable_no-intermediate_call.pyt
sila2codegenerator/templates/run-inline/command_observable_no-intermediate_implementation.pyt
sila2codegenerator/templates/run-inline/command_observable_no-intermediate_servicer.pyt
sila2codegenerator/templates/run-inline/command_unobservable_call.pyt
sila2codegenerator/templates/run-inline/command_unobservable_implementation.pyt
sila2codegenerator/templates/run-inline/command_unobservable_servicer.pyt
sila2codegenerator/templates/run-inline/feature_registration.pyt
sila2codegenerator/templates/run-inline/import_grpc.pyt
sila2codegenerator/templates/run-inline/import_servicer.pyt
sila2codegenerator/templates/run-inline/parameter_description.pyt
sila2codegenerator/templates/run-inline/property_observable_call.pyt
sila2codegenerator/templates/run-inline/property_observable_implementation.pyt
sila2codegenerator-0.2.0.dist-info/METADATA
sila2codegenerator-0.2.0.dist-info/WHEEL
sila2codegenerator-0.2.0.dist-info/entry_points.txt
sila2codegenerator-0.2.0.dist-info/top_level.txt
sila2codegenerator-0.2.0.dist-info/RECORD
