Metadata-Version: 2.1
Name: sila2codegenerator
Version: 0.2.0
Summary: SiLA2 code generator for Python3
Home-page: https://gitlab.com/SiLA2/sila_python
Author: Timm Severin, Mark Dörr
Author-email: mark.doerr@uni-greifswald.de
License: MIT
Keywords: SiLA2,codegenerator,lab automation,laboratory,instruments,experiments,evaluation,visualisation,serial interface,robots
Platform: UNKNOWN
Classifier: License :: OSI Approved :: MIT License
Classifier: Intended Audience :: Developers
Classifier: Operating System :: OS Independent
Classifier: Programming Language :: Python
Classifier: Programming Language :: Python :: 3.6
Classifier: Programming Language :: Python :: 3.7
Classifier: Topic :: Utilities
Classifier: Topic :: Scientific/Engineering
Classifier: Topic :: Scientific/Engineering :: Interface Engine/Protocol Translator
Classifier: Topic :: Scientific/Engineering :: Information Analysis
Requires-Dist: lxml
Requires-Dist: sila2lib
